MANIFEST.in
README.rst
setup.py
django_js_utils/__init__.py
django_js_utils/tests.py
django_js_utils/views.py
django_js_utils.egg-info/PKG-INFO
django_js_utils.egg-info/SOURCES.txt
django_js_utils.egg-info/dependency_links.txt
django_js_utils.egg-info/requires.txt
django_js_utils.egg-info/top_level.txt
django_js_utils/static/django_js_utils.js