Metadata-Version: 1.1
Name: django-js-utils
Version: 0.0.5dev
Summary: Utility library to help development of RIA on top of a Django backend
Home-page: UNKNOWN
Author: Vebjorn Ljosa
Author-email: vebjorn@ljosa.com
License: UNKNOWN
Platform: UNKNOWN
Classifier: License :: OSI Approved :: BSD License
Classifier: Programming Language :: Python
Classifier: Environment :: Web Environment
Classifier: Intended Audience :: Developers
Classifier: Operating System :: OS Independent
Classifier: Topic :: Internet :: WWW/HTTP
Classifier: Topic :: Utilities
